[{"name":"Noebi","player_id":2057131,"level":20,"charclass":"adventurer","alliance_id":1225,"y":16836,"x":44043,"duel_level":20,"inLevelRange":120,"inLevelRangeOpponent":-72,"isSleeping":false,"isSleepingFort":false,"isSleepingTent":false,"isFoundingFort":false,"alreadyDuelled":false,"last_duel":false,"nextDuel":null,"attackableByAnyone":false,"isDeadFlagged":false,"nextBattleAtLocation":null,"holiday_duel":true,"travel_distance":"0:00:21","exp":750,"distance":21,"hp":31,"rss":80,"rsp":87,"tct":16,"p":{"t":"j","id":51}},{"name":"Muriel","player_id":2067493,"level":49,"charclass":"adventurer","alliance_id":1165,"y":6721,"x":2838,"duel_level":51,"inLevelRange":337,"inLevelRangeOpponent":-227,"isSleeping":false,"isSleepingFort":false,"isSleepingTent":false,"isFoundingFort":false,"alreadyDuelled":false,"last_duel":false,"nextDuel":null,"attackableByAnyone":false,"isDeadFlagged":false,"nextBattleAtLocation":null,"holiday_duel":true,"travel_distance":"0:12:27","exp":2052,"distance":747,"hp":62,"rss":97,"rsp":80,"tct":60,"p":{"t":"j","id":27}},{"name":"Scalphunter","player_id":2059272,"level":32,"charclass":"adventurer","alliance_id":1225,"y":14341,"x":27157,"duel_level":32,"inLevelRange":204,"inLevelRangeOpponent":-132,"isSleeping":false,"isSleepingFort":false,"isSleepingTent":false,"isFoundingFort":false,"alreadyDuelled":false,"last_duel":false,"nextDuel":null,"attackableByAnyone":false,"isDeadFlagged":false,"nextBattleAtLocation":null,"holiday_duel":true,"travel_distance":"0:04:58","exp":1254,"distance":298,"hp":66,"rss":80,"rsp":101,"tct":27,"p":{"t":"j","id":45}},{"name":"Lucky Lelka","player_id":2065446,"level":62,"charclass":"duelist","alliance_id":1165,"y":6705,"x":18616,"duel_level":67,"inLevelRange":449,"inLevelRangeOpponent":-307,"isSleeping":false,"isSleepingFort":false,"isSleepingTent":false,"isFoundingFort":false,"alreadyDuelled":false,"last_duel":false,"nextDuel":null,"attackableByAnyone":false,"isDeadFlagged":false,"nextBattleAtLocation":null,"holiday_duel":true,"travel_distance":"0:08:04","exp":2724,"distance":484,"hp":104,"rss":146,"rsp":280,"tct":163,"p":{"t":"j","id":5}},{"name":"Lotus39","player_id":707376,"level":57,"charclass":"adventurer","alliance_id":1165,"y":4657,"x":16613,"duel_level":57,"inLevelRange":379,"inLevelRangeOpponent":-257,"isSleeping":false,"isSleepingFort":false,"isSleepingTent":false,"isFoundingFort":false,"alreadyDuelled":false,"last_duel":false,"nextDuel":null,"attackableByAnyone":false,"isDeadFlagged":false,"nextBattleAtLocation":null,"holiday_duel":true,"travel_distance":"0:08:52","exp":2304,"distance":532,"hp":115,"rss":133,"rsp":137,"tct":60,"p":{"t":"t","id":3077}},{"name":"OdDbAlL","player_id":2052559,"level":40,"charclass":"duelist","alliance_id":1225,"y":4580,"x":32380,"duel_level":40,"inLevelRange":260,"inLevelRangeOpponent":-172,"isSleeping":false,"isSleepingFort":false,"isSleepingTent":false,"isFoundingFort":false,"alreadyDuelled":false,"last_duel":false,"nextDuel":null,"attackableByAnyone":false,"isDeadFlagged":false,"nextBattleAtLocation":null,"holiday_duel":true,"travel_distance":"0:05:09","exp":1590,"distance":309,"hp":125,"rss":76,"rsp":62,"tct":19,"p":{"t":"j","id":38}},{"name":"StalkerUSP","player_id":1131926,"level":126,"charclass":"adventurer","alliance_id":1225,"y":9969,"x":28175,"duel_level":126,"inLevelRange":862,"inLevelRangeOpponent":-602,"isSleeping":false,"isSleepingFort":false,"isSleepingTent":false,"isFoundingFort":false,"alreadyDuelled":false,"last_duel":false,"nextDuel":null,"attackableByAnyone":false,"isDeadFlagged":false,"nextBattleAtLocation":null,"holiday_duel":true,"travel_distance":"0:05:07","exp":5202,"distance":307,"hp":151,"rss":316,"rsp":218,"tct":178,"p":{"t":"t","id":6451}},{"name":"Phibes","player_id":314577,"level":118,"charclass":"worker","alliance_id":1225,"y":5458,"x":29623,"duel_level":118,"inLevelRange":806,"inLevelRangeOpponent":-562,"isSleeping":false,"isSleepingFort":false,"isSleepingTent":false,"isFoundingFort":false,"alreadyDuelled":false,"last_duel":false,"nextDuel":null,"attackableByAnyone":false,"isDeadFlagged":false,"nextBattleAtLocation":null,"holiday_duel":true,"travel_distance":"0:05:31","exp":4866,"distance":331,"hp":220,"rss":120,"rsp":144,"tct":33,"p":{"t":"t","id":46}},{"name":"Miraculous","player_id":2046038,"level":149,"charclass":"duelist","alliance_id":1165,"y":5379,"x":16303,"duel_level":149,"inLevelRange":1023,"inLevelRangeOpponent":-717,"isSleeping":false,"isSleepingFort":false,"isSleepingTent":false,"isFoundingFort":false,"alreadyDuelled":false,"last_duel":false,"nextDuel":null,"attackableByAnyone":false,"isDeadFlagged":false,"nextBattleAtLocation":null,"holiday_duel":true,"travel_distance":"0:08:51","exp":6168,"distance":531,"hp":226,"rss":410,"rsp":406,"tct":691,"p":{"t":"j","id":115}},{"name":"Sydney*","player_id":112699,"level":119,"charclass":"worker","alliance_id":1165,"y":5379,"x":16303,"duel_level":122,"inLevelRange":834,"inLevelRangeOpponent":-582,"isSleeping":false,"isSleepingFort":false,"isSleepingTent":false,"isFoundingFort":false,"alreadyDuelled":false,"last_duel":false,"nextDuel":null,"attackableByAnyone":false,"isDeadFlagged":false,"nextBattleAtLocation":null,"holiday_duel":true,"travel_distance":"0:08:51","exp":5034,"distance":531,"hp":240,"rss":213,"rsp":205,"tct":114,"p":{"t":"j","id":115}},{"name":"AnnieO","player_id":2022671,"level":149,"charclass":"adventurer","alliance_id":1165,"y":18529,"x":24641,"duel_level":159,"inLevelRange":1093,"inLevelRangeOpponent":-767,"isSleeping":false,"isSleepingFort":false,"isSleepingTent":false,"isFoundingFort":false,"alreadyDuelled":false,"last_duel":false,"nextDuel":null,"attackableByAnyone":false,"isDeadFlagged":false,"nextBattleAtLocation":null,"holiday_duel":true,"travel_distance":"0:05:35","exp":6588,"distance":335,"hp":246,"rss":604,"rsp":274,"tct":108,"p":{"t":"j","id":41}},{"name":"Kaitie","player_id":2067263,"level":93,"charclass":"duelist","alliance_id":1165,"y":5472,"x":13775,"duel_level":93,"inLevelRange":631,"inLevelRangeOpponent":-437,"isSleeping":false,"isSleepingFort":false,"isSleepingTent":false,"isFoundingFort":false,"alreadyDuelled":false,"last_duel":false,"nextDuel":null,"attackableByAnyone":false,"isDeadFlagged":false,"nextBattleAtLocation":null,"holiday_duel":true,"travel_distance":"0:09:31","exp":3816,"distance":571,"hp":262,"rss":153,"rsp":240,"tct":68,"p":{"t":"j","id":30}},{"name":"Doodels","player_id":604843,"level":121,"charclass":"adventurer","alliance_id":1165,"y":11993,"x":2232,"duel_level":132,"inLevelRange":904,"inLevelRangeOpponent":-632,"isSleeping":false,"isSleepingFort":false,"isSleepingTent":false,"isFoundingFort":false,"alreadyDuelled":false,"last_duel":false,"nextDuel":null,"attackableByAnyone":false,"isDeadFlagged":false,"nextBattleAtLocation":null,"holiday_duel":true,"travel_distance":"0:12:18","exp":5454,"distance":738,"hp":268,"rss":418,"rsp":241,"tct":113,"p":{"t":"j","id":76}},{"name":"Eddie Richard","player_id":1913455,"level":181,"charclass":"duelist","alliance_id":1525,"y":12949,"x":27236,"duel_level":185,"inLevelRange":1275,"inLevelRangeOpponent":-897,"isSleeping":false,"isSleepingFort":false,"isSleepingTent":false,"isFoundingFort":false,"alreadyDuelled":false,"last_duel":false,"nextDuel":null,"attackableByAnyone":false,"isDeadFlagged":false,"nextBattleAtLocation":null,"holiday_duel":true,"travel_distance":"0:05:03","exp":7680,"distance":303,"hp":287,"rss":184,"rsp":187,"tct":476,"p":{"t":"j","id":114}},{"name":"Lady Mary","player_id":2042483,"level":133,"charclass":"adventurer","alliance_id":1525,"y":5382,"x":23245,"duel_level":133,"inLevelRange":911,"inLevelRangeOpponent":-637,"isSleeping":false,"isSleepingFort":false,"isSleepingTent":false,"isFoundingFort":false,"alreadyDuelled":false,"last_duel":false,"nextDuel":null,"attackableByAnyone":false,"isDeadFlagged":false,"nextBattleAtLocation":null,"holiday_duel":true,"travel_distance":"0:07:03","exp":5496,"distance":423,"hp":289,"rss":679,"rsp":351,"tct":161,"p":{"t":"j","id":44}},{"name":"Trixxer","player_id":1239064,"level":96,"charclass":"soldier","alliance_id":1165,"y":11005,"x":1990,"duel_level":96,"inLevelRange":652,"inLevelRangeOpponent":-452,"isSleeping":false,"isSleepingFort":false,"isSleepingTent":false,"isFoundingFort":false,"alreadyDuelled":false,"last_duel":false,"nextDuel":null,"attackableByAnyone":false,"isDeadFlagged":false,"nextBattleAtLocation":null,"holiday_duel":true,"travel_distance":"0:12:25","exp":3942,"distance":745,"hp":326,"rss":378,"rsp":442,"tct":120,"p":{"t":"t","id":1608}},{"name":"AV50","player_id":61604,"level":201,"charclass":"worker","alliance_id":1165,"y":15707,"x":23511,"duel_level":201,"inLevelRange":1387,"inLevelRangeOpponent":-977,"isSleeping":false,"isSleepingFort":false,"isSleepingTent":false,"isFoundingFort":false,"alreadyDuelled":false,"last_duel":false,"nextDuel":null,"attackableByAnyone":false,"isDeadFlagged":false,"nextBattleAtLocation":null,"holiday_duel":true,"travel_distance":"0:05:57","exp":8352,"distance":357,"hp":330,"rss":560,"rsp":397,"tct":786,"p":{"t":"j","id":117}},{"name":"01Nightwish01","player_id":572087,"level":192,"charclass":"adventurer","alliance_id":1165,"y":8244,"x":19767,"duel_level":197,"inLevelRange":1359,"inLevelRangeOpponent":-957,"isSleeping":false,"isSleepingFort":false,"isSleepingTent":false,"isFoundingFort":false,"alreadyDuelled":false,"last_duel":false,"nextDuel":null,"attackableByAnyone":false,"isDeadFlagged":false,"nextBattleAtLocation":null,"holiday_duel":true,"travel_distance":"0:07:35","exp":8184,"distance":455,"hp":355,"rss":1535,"rsp":598,"tct":356,"p":{"t":"j","id":64}},{"name":"Wastl","player_id":2064778,"level":98,"charclass":"duelist","alliance_id":1225,"y":1894,"x":30274,"duel_level":102,"inLevelRange":694,"inLevelRangeOpponent":-482,"isSleeping":false,"isSleepingFort":false,"isSleepingTent":false,"isFoundingFort":false,"alreadyDuelled":false,"last_duel":false,"nextDuel":null,"attackableByAnyone":false,"isDeadFlagged":false,"nextBattleAtLocation":null,"holiday_duel":true,"travel_distance":"0:06:09","exp":4194,"distance":369,"hp":366,"rss":236,"rsp":270,"tct":91,"p":{"t":"j","id":26}},{"name":"whitetiger666","player_id":1084700,"level":166,"charclass":"adventurer","alliance_id":1225,"y":17375,"x":10410,"duel_level":166,"inLevelRange":1142,"inLevelRangeOpponent":-802,"isSleeping":false,"isSleepingFort":false,"isSleepingTent":false,"isFoundingFort":false,"alreadyDuelled":false,"last_duel":false,"nextDuel":null,"attackableByAnyone":false,"isDeadFlagged":false,"nextBattleAtLocation":null,"holiday_duel":true,"travel_distance":"0:09:46","exp":6882,"distance":586,"hp":381,"rss":318,"rsp":311,"tct":175,"p":{"t":"j","id":30}},{"name":"Retrieve","player_id":2045125,"level":123,"charclass":"adventurer","alliance_id":1165,"y":13897,"x":11355,"duel_level":123,"inLevelRange":841,"inLevelRangeOpponent":-587,"isSleeping":false,"isSleepingFort":false,"isSleepingTent":false,"isFoundingFort":false,"alreadyDuelled":false,"last_duel":false,"nextDuel":null,"attackableByAnyone":false,"isDeadFlagged":false,"nextBattleAtLocation":null,"holiday_duel":true,"travel_distance":"0:09:34","exp":5076,"distance":574,"hp":415,"rss":661,"rsp":371,"tct":79,"p":{"t":"j","id":17}},{"name":"*Sando*","player_id":1264807,"level":187,"charclass":"adventurer","alliance_id":1165,"y":11005,"x":1990,"duel_level":187,"inLevelRange":1289,"inLevelRangeOpponent":-907,"isSleeping":false,"isSleepingFort":false,"isSleepingTent":false,"isFoundingFort":false,"alreadyDuelled":false,"last_duel":false,"nextDuel":null,"attackableByAnyone":false,"isDeadFlagged":false,"nextBattleAtLocation":null,"holiday_duel":true,"travel_distance":"0:12:25","exp":7764,"distance":745,"hp":473,"rss":422,"rsp":494,"tct":648,"p":{"t":"t","id":1608}},{"name":"Dorothy","player_id":211421,"level":182,"charclass":"worker","alliance_id":1165,"y":19326,"x":22772,"duel_level":182,"inLevelRange":1254,"inLevelRangeOpponent":-882,"isSleeping":false,"isSleepingFort":false,"isSleepingTent":false,"isFoundingFort":false,"alreadyDuelled":false,"last_duel":false,"nextDuel":null,"attackableByAnyone":false,"isDeadFlagged":false,"nextBattleAtLocation":null,"holiday_duel":true,"travel_distance":"0:06:09","exp":7554,"distance":369,"hp":475,"rss":313,"rsp":334,"tct":206,"p":{"t":"j","id":25}},{"name":"M.Myers","player_id":187778,"level":178,"charclass":"duelist","alliance_id":1165,"y":11437,"x":11500,"duel_level":178,"inLevelRange":1226,"inLevelRangeOpponent":-862,"isSleeping":false,"isSleepingFort":false,"isSleepingTent":false,"isFoundingFort":false,"alreadyDuelled":false,"last_duel":false,"nextDuel":null,"attackableByAnyone":false,"isDeadFlagged":false,"nextBattleAtLocation":null,"holiday_duel":true,"travel_distance":"0:09:39","exp":7386,"distance":579,"hp":483,"rss":1902,"rsp":866,"tct":94,"p":{"t":"j","id":85}},{"name":"Schnuffeltuch","player_id":2067008,"level":76,"charclass":"soldier","alliance_id":1165,"y":11800,"x":10457,"duel_level":79,"inLevelRange":533,"inLevelRangeOpponent":-367,"isSleeping":false,"isSleepingFort":false,"isSleepingTent":false,"isFoundingFort":false,"alreadyDuelled":false,"last_duel":false,"nextDuel":null,"attackableByAnyone":false,"isDeadFlagged":false,"nextBattleAtLocation":null,"holiday_duel":true,"travel_distance":"0:09:56","exp":3228,"distance":596,"hp":498,"rss":138,"rsp":213,"tct":102,"p":{"t":"j","id":107}},{"name":"Engels1962","player_id":630004,"level":181,"charclass":"duelist","alliance_id":1165,"y":6721,"x":2838,"duel_level":204,"inLevelRange":1408,"inLevelRangeOpponent":-992,"isSleeping":false,"isSleepingFort":false,"isSleepingTent":false,"isFoundingFort":false,"alreadyDuelled":false,"last_duel":false,"nextDuel":null,"attackableByAnyone":false,"isDeadFlagged":false,"nextBattleAtLocation":null,"holiday_duel":true,"travel_distance":"0:12:27","exp":8478,"distance":747,"hp":526,"rss":281,"rsp":435,"tct":96,"p":{"t":"j","id":27}},{"name":"Dr-Strom","player_id":789557,"level":191,"charclass":"worker","alliance_id":1165,"y":2868,"x":833,"duel_level":191,"inLevelRange":1317,"inLevelRangeOpponent":-927,"isSleeping":false,"isSleepingFort":false,"isSleepingTent":false,"isFoundingFort":false,"alreadyDuelled":false,"last_duel":false,"nextDuel":null,"attackableByAnyone":false,"isDeadFlagged":false,"nextBattleAtLocation":null,"holiday_duel":true,"travel_distance":"0:13:21","exp":7932,"distance":801,"hp":532,"rss":328,"rsp":340,"tct":212,"p":{"t":"j","id":11}},{"name":"FrauMileHigh","player_id":757828,"level":195,"charclass":"soldier","alliance_id":1165,"y":3937,"x":40513,"duel_level":198,"inLevelRange":1366,"inLevelRangeOpponent":-962,"isSleeping":false,"isSleepingFort":false,"isSleepingTent":false,"isFoundingFort":false,"alreadyDuelled":false,"last_duel":false,"nextDuel":null,"attackableByAnyone":false,"isDeadFlagged":false,"nextBattleAtLocation":null,"holiday_duel":true,"travel_distance":"0:04:13","exp":8226,"distance":253,"hp":547,"rss":364,"rsp":399,"tct":1200,"p":{"t":"j","id":118}},{"name":"Arya Stark","player_id":2043013,"level":154,"charclass":"adventurer","alliance_id":1165,"y":11005,"x":1990,"duel_level":154,"inLevelRange":1058,"inLevelRangeOpponent":-742,"isSleeping":false,"isSleepingFort":false,"isSleepingTent":false,"isFoundingFort":false,"alreadyDuelled":false,"last_duel":false,"nextDuel":null,"attackableByAnyone":false,"isDeadFlagged":false,"nextBattleAtLocation":null,"holiday_duel":true,"travel_distance":"0:12:25","exp":6378,"distance":745,"hp":563,"rss":644,"rsp":520,"tct":91,"p":{"t":"t","id":1608}},{"name":"Roglom","player_id":467794,"level":192,"charclass":"adventurer","alliance_id":1165,"y":4571,"x":15432,"duel_level":201,"inLevelRange":1387,"inLevelRangeOpponent":-977,"isSleeping":false,"isSleepingFort":false,"isSleepingTent":false,"isFoundingFort":false,"alreadyDuelled":false,"last_duel":false,"nextDuel":null,"attackableByAnyone":false,"isDeadFlagged":false,"nextBattleAtLocation":null,"holiday_duel":true,"travel_distance":"0:09:11","exp":8352,"distance":551,"hp":574,"rss":128,"rsp":167,"tct":859,"p":{"t":"j","id":95}},{"name":"DarkCount","player_id":802252,"level":186,"charclass":"adventurer","alliance_id":1225,"y":2711,"x":2076,"duel_level":186,"inLevelRange":1282,"inLevelRangeOpponent":-902,"isSleeping":false,"isSleepingFort":false,"isSleepingTent":false,"isFoundingFort":false,"alreadyDuelled":false,"last_duel":false,"nextDuel":null,"attackableByAnyone":false,"isDeadFlagged":false,"nextBattleAtLocation":null,"holiday_duel":true,"travel_distance":"0:13:01","exp":7722,"distance":781,"hp":590,"rss":985,"rsp":461,"tct":237,"p":{"t":"j","id":68}},{"name":"JohnCoold","player_id":1933153,"level":187,"charclass":"adventurer","alliance_id":1225,"y":15532,"x":27472,"duel_level":191,"inLevelRange":1317,"inLevelRangeOpponent":-927,"isSleeping":false,"isSleepingFort":false,"isSleepingTent":false,"isFoundingFort":false,"alreadyDuelled":false,"last_duel":false,"nextDuel":null,"attackableByAnyone":false,"isDeadFlagged":false,"nextBattleAtLocation":null,"holiday_duel":true,"travel_distance":"0:04:48","exp":7932,"distance":288,"hp":597,"rss":338,"rsp":330,"tct":216,"p":{"t":"j","id":1}},{"name":"Schnellerwolf","player_id":2032116,"level":124,"charclass":"duelist","alliance_id":1165,"y":14226,"x":22413,"duel_level":131,"inLevelRange":897,"inLevelRangeOpponent":-627,"isSleeping":false,"isSleepingFort":false,"isSleepingTent":false,"isFoundingFort":false,"alreadyDuelled":false,"last_duel":false,"nextDuel":null,"attackableByAnyone":false,"isDeadFlagged":false,"nextBattleAtLocation":null,"holiday_duel":true,"travel_distance":"0:06:20","exp":5412,"distance":380,"hp":603,"rss":456,"rsp":456,"tct":522,"p":{"t":"t","id":3107}},{"name":"Lares","player_id":6204,"level":194,"charclass":"adventurer","alliance_id":1225,"y":11301,"x":27763,"duel_level":194,"inLevelRange":1338,"inLevelRangeOpponent":-942,"isSleeping":false,"isSleepingFort":false,"isSleepingTent":false,"isFoundingFort":false,"alreadyDuelled":false,"last_duel":false,"nextDuel":null,"attackableByAnyone":false,"isDeadFlagged":false,"nextBattleAtLocation":null,"holiday_duel":true,"travel_distance":"0:05:04","exp":8058,"distance":304,"hp":644,"rss":267,"rsp":282,"tct":971,"p":{"t":"j","id":18}},{"name":"Blem","player_id":102473,"level":191,"charclass":"adventurer","alliance_id":1165,"y":16148,"x":16778,"duel_level":206,"inLevelRange":1422,"inLevelRangeOpponent":-1002,"isSleeping":false,"isSleepingFort":false,"isSleepingTent":false,"isFoundingFort":false,"alreadyDuelled":false,"last_duel":false,"nextDuel":null,"attackableByAnyone":false,"isDeadFlagged":false,"nextBattleAtLocation":null,"holiday_duel":true,"travel_distance":"0:07:55","exp":8562,"distance":475,"hp":650,"rss":829,"rsp":404,"tct":299,"p":{"t":"j","id":73}},{"name":"merlin388","player_id":77080,"level":186,"charclass":"adventurer","alliance_id":1165,"y":4832,"x":30740,"duel_level":198,"inLevelRange":1366,"inLevelRangeOpponent":-962,"isSleeping":false,"isSleepingFort":false,"isSleepingTent":false,"isFoundingFort":false,"alreadyDuelled":false,"last_duel":false,"nextDuel":null,"attackableByAnyone":false,"isDeadFlagged":false,"nextBattleAtLocation":null,"holiday_duel":true,"travel_distance":"0:05:25","exp":8226,"distance":325,"hp":659,"rss":284,"rsp":197,"tct":194,"p":{"t":"j","id":65}},{"name":"The Explorer","player_id":449382,"level":198,"charclass":"adventurer","alliance_id":1165,"y":15206,"x":14970,"duel_level":212,"inLevelRange":1464,"inLevelRangeOpponent":-1032,"isSleeping":false,"isSleepingFort":false,"isSleepingTent":false,"isFoundingFort":false,"alreadyDuelled":false,"last_duel":false,"nextDuel":null,"attackableByAnyone":false,"isDeadFlagged":false,"nextBattleAtLocation":null,"holiday_duel":true,"travel_distance":"0:08:28","exp":8814,"distance":508,"hp":669,"rss":509,"rsp":1429,"tct":110,"p":{"t":"j","id":13}},{"name":"Cumano","player_id":716039,"level":170,"charclass":"soldier","alliance_id":1165,"y":19563,"x":10443,"duel_level":170,"inLevelRange":1170,"inLevelRangeOpponent":-822,"isSleeping":false,"isSleepingFort":false,"isSleepingTent":false,"isFoundingFort":false,"alreadyDuelled":false,"last_duel":false,"nextDuel":null,"attackableByAnyone":false,"isDeadFlagged":false,"nextBattleAtLocation":null,"holiday_duel":true,"travel_distance":"0:09:46","exp":7050,"distance":586,"hp":712,"rss":431,"rsp":230,"tct":260,"p":{"t":"t","id":1242}},{"name":"Paul Tracy","player_id":1952720,"level":159,"charclass":"duelist","alliance_id":1225,"y":6386,"x":31061,"duel_level":159,"inLevelRange":1093,"inLevelRangeOpponent":-767,"isSleeping":false,"isSleepingFort":false,"isSleepingTent":false,"isFoundingFort":false,"alreadyDuelled":false,"last_duel":false,"nextDuel":null,"attackableByAnyone":false,"isDeadFlagged":false,"nextBattleAtLocation":null,"holiday_duel":true,"travel_distance":"0:05:02","exp":6588,"distance":302,"hp":719,"rss":159,"rsp":136,"tct":294,"p":{"t":"j","id":115}},{"name":"JoMickus","player_id":1048480,"level":179,"charclass":"adventurer","alliance_id":1165,"y":7896,"x":16004,"duel_level":179,"inLevelRange":1233,"inLevelRangeOpponent":-867,"isSleeping":false,"isSleepingFort":false,"isSleepingTent":false,"isFoundingFort":false,"alreadyDuelled":false,"last_duel":false,"nextDuel":null,"attackableByAnyone":false,"isDeadFlagged":false,"nextBattleAtLocation":null,"holiday_duel":true,"travel_distance":"0:08:39","exp":7428,"distance":519,"hp":740,"rss":316,"rsp":322,"tct":160,"p":{"t":"j","id":19}},{"name":"Emha","player_id":636984,"level":190,"charclass":"adventurer","alliance_id":1165,"y":8549,"x":17435,"duel_level":208,"inLevelRange":1436,"inLevelRangeOpponent":-1012,"isSleeping":false,"isSleepingFort":false,"isSleepingTent":false,"isFoundingFort":false,"alreadyDuelled":false,"last_duel":false,"nextDuel":null,"attackableByAnyone":false,"isDeadFlagged":false,"nextBattleAtLocation":null,"holiday_duel":true,"travel_distance":"0:08:11","exp":8646,"distance":491,"hp":741,"rss":428,"rsp":544,"tct":535,"p":{"t":"j","id":71}},{"name":"tjoster","player_id":553473,"level":190,"charclass":"soldier","alliance_id":1165,"y":1411,"x":33845,"duel_level":222,"inLevelRange":1534,"inLevelRangeOpponent":-1082,"isSleeping":false,"isSleepingFort":false,"isSleepingTent":false,"isFoundingFort":false,"alreadyDuelled":false,"last_duel":false,"nextDuel":null,"attackableByAnyone":false,"isDeadFlagged":false,"nextBattleAtLocation":null,"holiday_duel":true,"travel_distance":"0:05:39","exp":9234,"distance":339,"hp":776,"rss":265,"rsp":274,"tct":617,"p":{"t":"j","id":87}},{"name":"sojatante","player_id":1946393,"level":138,"charclass":"duelist","alliance_id":1165,"y":12439,"x":11323,"duel_level":138,"inLevelRange":946,"inLevelRangeOpponent":-662,"isSleeping":false,"isSleepingFort":false,"isSleepingTent":false,"isFoundingFort":false,"alreadyDuelled":false,"last_duel":false,"nextDuel":null,"attackableByAnyone":false,"isDeadFlagged":false,"nextBattleAtLocation":null,"holiday_duel":true,"travel_distance":"0:09:39","exp":5706,"distance":579,"hp":835,"rss":187,"rsp":262,"tct":104,"p":{"t":"t","id":212}},{"name":"JOHN 02","player_id":418602,"level":192,"charclass":"adventurer","alliance_id":1225,"y":11714,"x":28788,"duel_level":232,"inLevelRange":1604,"inLevelRangeOpponent":-1132,"isSleeping":false,"isSleepingFort":false,"isSleepingTent":false,"isFoundingFort":false,"alreadyDuelled":false,"last_duel":false,"nextDuel":null,"attackableByAnyone":false,"isDeadFlagged":false,"nextBattleAtLocation":null,"holiday_duel":true,"travel_distance":"0:04:44","exp":9654,"distance":284,"hp":844,"rss":325,"rsp":273,"tct":633,"p":{"t":"t","id":6464}},{"name":"?JjjjJ?","player_id":390845,"level":187,"charclass":"adventurer","alliance_id":1165,"y":5296,"x":20369,"duel_level":258,"inLevelRange":1786,"inLevelRangeOpponent":-1262,"isSleeping":false,"isSleepingFort":false,"isSleepingTent":false,"isFoundingFort":false,"alreadyDuelled":false,"last_duel":false,"nextDuel":null,"attackableByAnyone":false,"isDeadFlagged":false,"nextBattleAtLocation":null,"holiday_duel":true,"travel_distance":"0:07:47","exp":10746,"distance":467,"hp":862,"rss":334,"rsp":470,"tct":1414,"p":{"t":"j","id":109}},{"name":"Fitsche","player_id":369529,"level":185,"charclass":"adventurer","alliance_id":1165,"y":1789,"x":23687,"duel_level":185,"inLevelRange":1275,"inLevelRangeOpponent":-897,"isSleeping":false,"isSleepingFort":false,"isSleepingTent":false,"isFoundingFort":false,"alreadyDuelled":false,"last_duel":false,"nextDuel":null,"attackableByAnyone":false,"isDeadFlagged":false,"nextBattleAtLocation":null,"holiday_duel":true,"travel_distance":"0:07:33","exp":7680,"distance":453,"hp":866,"rss":297,"rsp":446,"tct":188,"p":{"t":"j","id":98}},{"name":"TechnoCop","player_id":657598,"level":193,"charclass":"soldier","alliance_id":1165,"y":16788,"x":29944,"duel_level":216,"inLevelRange":1492,"inLevelRangeOpponent":-1052,"isSleeping":false,"isSleepingFort":false,"isSleepingTent":false,"isFoundingFort":false,"alreadyDuelled":false,"last_duel":false,"nextDuel":null,"attackableByAnyone":false,"isDeadFlagged":false,"nextBattleAtLocation":null,"holiday_duel":true,"travel_distance":"0:04:03","exp":8982,"distance":243,"hp":867,"rss":310,"rsp":314,"tct":521,"p":{"t":"j","id":45}},{"name":"Wild Bill Hickok-2015","player_id":1975023,"level":174,"charclass":"adventurer","alliance_id":1165,"y":16478,"x":8381,"duel_level":179,"inLevelRange":1233,"inLevelRangeOpponent":-867,"isSleeping":false,"isSleepingFort":false,"isSleepingTent":false,"isFoundingFort":false,"alreadyDuelled":false,"last_duel":false,"nextDuel":null,"attackableByAnyone":false,"isDeadFlagged":false,"nextBattleAtLocation":null,"holiday_duel":true,"travel_distance":"0:10:23","exp":7428,"distance":623,"hp":890,"rss":420,"rsp":521,"tct":110,"p":{"t":"t","id":85}},{"name":"Swanheart","player_id":614759,"level":194,"charclass":"soldier","alliance_id":1165,"y":455,"x":17101,"duel_level":216,"inLevelRange":1492,"inLevelRangeOpponent":-1052,"isSleeping":false,"isSleepingFort":false,"isSleepingTent":false,"isFoundingFort":false,"alreadyDuelled":false,"last_duel":false,"nextDuel":null,"attackableByAnyone":false,"isDeadFlagged":false,"nextBattleAtLocation":null,"holiday_duel":true,"travel_distance":"0:09:21","exp":8982,"distance":561,"hp":894,"rss":1731,"rsp":738,"tct":308,"p":{"t":"j","id":77}},{"name":"lutz69","player_id":744430,"level":197,"charclass":"duelist","alliance_id":1165,"y":16227,"x":764,"duel_level":220,"inLevelRange":1520,"inLevelRangeOpponent":-1072,"isSleeping":false,"isSleepingFort":false,"isSleepingTent":false,"isFoundingFort":false,"alreadyDuelled":false,"last_duel":false,"nextDuel":null,"attackableByAnyone":false,"isDeadFlagged":false,"nextBattleAtLocation":null,"holiday_duel":true,"travel_distance":"0:12:37","exp":9150,"distance":757,"hp":917,"rss":568,"rsp":625,"tct":821,"p":{"t":"j","id":79}},{"name":"Tina2411","player_id":2024468,"level":146,"charclass":"duelist","alliance_id":1225,"y":6205,"x":19152,"duel_level":146,"inLevelRange":1002,"inLevelRangeOpponent":-702,"isSleeping":false,"isSleepingFort":false,"isSleepingTent":false,"isFoundingFort":false,"alreadyDuelled":false,"last_duel":false,"nextDuel":null,"attackableByAnyone":false,"isDeadFlagged":false,"nextBattleAtLocation":null,"holiday_duel":true,"travel_distance":"0:07:59","exp":6042,"distance":479,"hp":946,"rss":270,"rsp":436,"tct":66,"p":{"t":"j","id":59}},{"name":"Nummy-33","player_id":381492,"level":193,"charclass":"soldier","alliance_id":1165,"y":2382,"x":22515,"duel_level":199,"inLevelRange":1373,"inLevelRangeOpponent":-967,"isSleeping":false,"isSleepingFort":false,"isSleepingTent":false,"isFoundingFort":false,"alreadyDuelled":false,"last_duel":false,"nextDuel":null,"attackableByAnyone":false,"isDeadFlagged":false,"nextBattleAtLocation":null,"holiday_duel":true,"travel_distance":"0:07:43","exp":8268,"distance":463,"hp":973,"rss":307,"rsp":279,"tct":243,"p":{"t":"j","id":113}},{"name":"thejulian","player_id":1150942,"level":186,"charclass":"soldier","alliance_id":1165,"y":6288,"x":4199,"duel_level":210,"inLevelRange":1450,"inLevelRangeOpponent":-1022,"isSleeping":false,"isSleepingFort":false,"isSleepingTent":false,"isFoundingFort":false,"alreadyDuelled":false,"last_duel":false,"nextDuel":null,"attackableByAnyone":false,"isDeadFlagged":false,"nextBattleAtLocation":null,"holiday_duel":true,"travel_distance":"0:12:06","exp":8730,"distance":726,"hp":980,"rss":1168,"rsp":1077,"tct":176,"p":{"t":"j","id":61}},{"name":"Lemmy64","player_id":309908,"level":192,"charclass":"soldier","alliance_id":1165,"y":15126,"x":25237,"duel_level":217,"inLevelRange":1499,"inLevelRangeOpponent":-1057,"isSleeping":false,"isSleepingFort":false,"isSleepingTent":false,"isFoundingFort":false,"alreadyDuelled":false,"last_duel":false,"nextDuel":null,"attackableByAnyone":false,"isDeadFlagged":false,"nextBattleAtLocation":null,"holiday_duel":true,"travel_distance":"0:05:29","exp":9024,"distance":329,"hp":1046,"rss":349,"rsp":416,"tct":315,"p":{"t":"j","id":62}},{"name":"Petzibär1977","player_id":2051705,"level":171,"charclass":"adventurer","alliance_id":1165,"y":11032,"x":10891,"duel_level":179,"inLevelRange":1233,"inLevelRangeOpponent":-867,"isSleeping":false,"isSleepingFort":false,"isSleepingTent":false,"isFoundingFort":false,"alreadyDuelled":false,"last_duel":false,"nextDuel":null,"attackableByAnyone":false,"isDeadFlagged":false,"nextBattleAtLocation":null,"holiday_duel":true,"travel_distance":"0:09:51","exp":7428,"distance":591,"hp":1055,"rss":266,"rsp":399,"tct":91,"p":{"t":"j","id":54}},{"name":"biesti81","player_id":575903,"level":192,"charclass":"adventurer","alliance_id":1225,"y":1537,"x":3294,"duel_level":192,"inLevelRange":1324,"inLevelRangeOpponent":-932,"isSleeping":false,"isSleepingFort":false,"isSleepingTent":false,"isFoundingFort":false,"alreadyDuelled":false,"last_duel":false,"nextDuel":null,"attackableByAnyone":false,"isDeadFlagged":false,"nextBattleAtLocation":null,"holiday_duel":true,"travel_distance":"0:12:49","exp":7974,"distance":769,"hp":1066,"rss":213,"rsp":210,"tct":130,"p":{"t":"j","id":15}},{"name":"nachtblume333","player_id":578465,"level":196,"charclass":"adventurer","alliance_id":1225,"y":12881,"x":969,"duel_level":233,"inLevelRange":1611,"inLevelRangeOpponent":-1137,"isSleeping":false,"isSleepingFort":false,"isSleepingTent":false,"isFoundingFort":false,"alreadyDuelled":false,"last_duel":false,"nextDuel":null,"attackableByAnyone":false,"isDeadFlagged":false,"nextBattleAtLocation":null,"holiday_duel":true,"travel_distance":"0:12:38","exp":9696,"distance":758,"hp":1184,"rss":1619,"rsp":716,"tct":141,"p":{"t":"j","id":13}},{"name":"123mausi","player_id":889725,"level":192,"charclass":"adventurer","alliance_id":1225,"y":18529,"x":24641,"duel_level":192,"inLevelRange":1324,"inLevelRangeOpponent":-932,"isSleeping":false,"isSleepingFort":false,"isSleepingTent":false,"isFoundingFort":false,"alreadyDuelled":false,"last_duel":false,"nextDuel":null,"attackableByAnyone":false,"isDeadFlagged":false,"nextBattleAtLocation":null,"holiday_duel":true,"travel_distance":"0:05:35","exp":7974,"distance":335,"hp":1185,"rss":584,"rsp":1318,"tct":256,"p":{"t":"j","id":41}},{"name":"Civilationsherrscher","player_id":905810,"level":192,"charclass":"soldier","alliance_id":1165,"y":14032,"x":31470,"duel_level":210,"inLevelRange":1450,"inLevelRangeOpponent":-1022,"isSleeping":false,"isSleepingFort":false,"isSleepingTent":false,"isFoundingFort":false,"alreadyDuelled":false,"last_duel":false,"nextDuel":null,"attackableByAnyone":false,"isDeadFlagged":false,"nextBattleAtLocation":null,"holiday_duel":true,"travel_distance":"0:03:46","exp":8730,"distance":226,"hp":1268,"rss":436,"rsp":454,"tct":1187,"p":{"t":"j","id":67}},{"name":"Gila","player_id":757259,"level":221,"charclass":"soldier","alliance_id":1165,"y":5558,"x":39288,"duel_level":221,"inLevelRange":1527,"inLevelRangeOpponent":-1077,"isSleeping":false,"isSleepingFort":false,"isSleepingTent":false,"isFoundingFort":false,"alreadyDuelled":false,"last_duel":false,"nextDuel":null,"attackableByAnyone":false,"isDeadFlagged":false,"nextBattleAtLocation":null,"holiday_duel":true,"travel_distance":"0:03:52","exp":9192,"distance":232,"hp":1319,"rss":192,"rsp":604,"tct":248,"p":{"t":"t","id":1407}},{"name":"Conchitta","player_id":2002929,"level":183,"charclass":"adventurer","alliance_id":1165,"y":11663,"x":11011,"duel_level":183,"inLevelRange":1261,"inLevelRangeOpponent":-887,"isSleeping":false,"isSleepingFort":false,"isSleepingTent":false,"isFoundingFort":false,"alreadyDuelled":false,"last_duel":false,"nextDuel":null,"attackableByAnyone":false,"isDeadFlagged":false,"nextBattleAtLocation":null,"holiday_duel":true,"travel_distance":"0:09:46","exp":7596,"distance":586,"hp":1327,"rss":1424,"rsp":751,"tct":98,"p":{"t":"j","id":97}},{"name":"Sheikh Marco","player_id":128557,"level":191,"charclass":"adventurer","alliance_id":1225,"y":6241,"x":27709,"duel_level":204,"inLevelRange":1408,"inLevelRangeOpponent":-992,"isSleeping":false,"isSleepingFort":false,"isSleepingTent":false,"isFoundingFort":false,"alreadyDuelled":false,"last_duel":false,"nextDuel":null,"attackableByAnyone":false,"isDeadFlagged":false,"nextBattleAtLocation":null,"holiday_duel":true,"travel_distance":"0:05:49","exp":8478,"distance":349,"hp":1337,"rss":1285,"rsp":1159,"tct":265,"p":{"t":"j","id":107}},{"name":"3apfelstrudel","player_id":359376,"level":187,"charclass":"soldier","alliance_id":1225,"y":7009,"x":6844,"duel_level":201,"inLevelRange":1387,"inLevelRangeOpponent":-977,"isSleeping":false,"isSleepingFort":false,"isSleepingTent":false,"isFoundingFort":false,"alreadyDuelled":false,"last_duel":false,"nextDuel":null,"attackableByAnyone":false,"isDeadFlagged":false,"nextBattleAtLocation":null,"holiday_duel":true,"travel_distance":"0:11:17","exp":8352,"distance":677,"hp":1363,"rss":570,"rsp":588,"tct":1131,"p":{"t":"j","id":65}},{"name":"kleinemomi","player_id":572086,"level":195,"charclass":"adventurer","alliance_id":1165,"y":9950,"x":11980,"duel_level":218,"inLevelRange":1506,"inLevelRangeOpponent":-1062,"isSleeping":false,"isSleepingFort":false,"isSleepingTent":false,"isFoundingFort":false,"alreadyDuelled":false,"last_duel":false,"nextDuel":null,"attackableByAnyone":false,"isDeadFlagged":false,"nextBattleAtLocation":null,"holiday_duel":true,"travel_distance":"0:09:36","exp":9066,"distance":576,"hp":1446,"rss":1605,"rsp":838,"tct":111,"p":{"t":"j","id":99}},{"name":"Di Morrissey","player_id":1949930,"level":169,"charclass":"adventurer","alliance_id":1165,"y":12675,"x":11504,"duel_level":169,"inLevelRange":1163,"inLevelRangeOpponent":-817,"isSleeping":false,"isSleepingFort":false,"isSleepingTent":false,"isFoundingFort":false,"alreadyDuelled":false,"last_duel":false,"nextDuel":null,"attackableByAnyone":false,"isDeadFlagged":false,"nextBattleAtLocation":null,"holiday_duel":true,"travel_distance":"0:09:35","exp":7008,"distance":575,"hp":1455,"rss":325,"rsp":420,"tct":95,"p":{"t":"j","id":9}},{"name":"Altersham","player_id":257861,"level":182,"charclass":"soldier","alliance_id":1225,"y":6939,"x":2204,"duel_level":205,"inLevelRange":1415,"inLevelRangeOpponent":-997,"isSleeping":false,"isSleepingFort":false,"isSleepingTent":false,"isFoundingFort":false,"alreadyDuelled":false,"last_duel":false,"nextDuel":null,"attackableByAnyone":false,"isDeadFlagged":false,"nextBattleAtLocation":null,"holiday_duel":true,"travel_distance":"0:12:37","exp":8520,"distance":757,"hp":1464,"rss":263,"rsp":207,"tct":507,"p":{"t":"j","id":121}},{"name":"lilakuh34","player_id":2019714,"level":173,"charclass":"duelist","alliance_id":1165,"y":11882,"x":11608,"duel_level":178,"inLevelRange":1226,"inLevelRangeOpponent":-862,"isSleeping":false,"isSleepingFort":false,"isSleepingTent":false,"isFoundingFort":false,"alreadyDuelled":false,"last_duel":false,"nextDuel":null,"attackableByAnyone":false,"isDeadFlagged":false,"nextBattleAtLocation":null,"holiday_duel":true,"travel_distance":"0:09:35","exp":7386,"distance":575,"hp":1471,"rss":831,"rsp":564,"tct":136,"p":{"t":"j","id":28}},{"name":"La Cucaracha Mama","player_id":492686,"level":193,"charclass":"adventurer","alliance_id":1165,"y":4168,"x":15359,"duel_level":214,"inLevelRange":1478,"inLevelRangeOpponent":-1042,"isSleeping":false,"isSleepingFort":false,"isSleepingTent":false,"isFoundingFort":false,"alreadyDuelled":false,"last_duel":false,"nextDuel":null,"attackableByAnyone":false,"isDeadFlagged":false,"nextBattleAtLocation":null,"holiday_duel":true,"travel_distance":"0:09:15","exp":8898,"distance":555,"hp":1490,"rss":272,"rsp":501,"tct":169,"p":{"t":"j","id":127}},{"name":"Cronus","player_id":145355,"level":193,"charclass":"adventurer","alliance_id":1225,"y":13931,"x":8824,"duel_level":206,"inLevelRange":1422,"inLevelRangeOpponent":-1002,"isSleeping":false,"isSleepingFort":false,"isSleepingTent":false,"isFoundingFort":false,"alreadyDuelled":false,"last_duel":false,"nextDuel":null,"attackableByAnyone":false,"isDeadFlagged":false,"nextBattleAtLocation":null,"holiday_duel":true,"travel_distance":"0:10:18","exp":8562,"distance":618,"hp":1538,"rss":382,"rsp":889,"tct":90,"p":{"t":"j","id":78}},{"name":"waisen","player_id":1029838,"level":191,"charclass":"worker","alliance_id":1165,"y":7389,"x":15798,"duel_level":204,"inLevelRange":1408,"inLevelRangeOpponent":-992,"isSleeping":false,"isSleepingFort":false,"isSleepingTent":false,"isFoundingFort":false,"alreadyDuelled":false,"last_duel":false,"nextDuel":null,"attackableByAnyone":false,"isDeadFlagged":false,"nextBattleAtLocation":null,"holiday_duel":true,"travel_distance":"0:08:45","exp":8478,"distance":525,"hp":1556,"rss":276,"rsp":521,"tct":158,"p":{"t":"j","id":77}},{"name":"Redwhiteinside","player_id":75538,"level":154,"charclass":"duelist","alliance_id":1165,"y":11032,"x":10891,"duel_level":161,"inLevelRange":1107,"inLevelRangeOpponent":-777,"isSleeping":false,"isSleepingFort":false,"isSleepingTent":false,"isFoundingFort":false,"alreadyDuelled":false,"last_duel":false,"nextDuel":null,"attackableByAnyone":false,"isDeadFlagged":false,"nextBattleAtLocation":null,"holiday_duel":true,"travel_distance":"0:09:51","exp":6672,"distance":591,"hp":1556,"rss":872,"rsp":454,"tct":63,"p":{"t":"j","id":54}},{"name":"BridgetJones","player_id":715607,"level":181,"charclass":"duelist","alliance_id":1165,"y":3737,"x":10236,"duel_level":240,"inLevelRange":1660,"inLevelRangeOpponent":-1172,"isSleeping":false,"isSleepingFort":false,"isSleepingTent":false,"isFoundingFort":false,"alreadyDuelled":false,"last_duel":false,"nextDuel":null,"attackableByAnyone":false,"isDeadFlagged":false,"nextBattleAtLocation":null,"holiday_duel":true,"travel_distance":"0:10:41","exp":9990,"distance":641,"hp":1583,"rss":226,"rsp":259,"tct":328,"p":{"t":"j","id":19}},{"name":"aquatania","player_id":103674,"level":152,"charclass":"adventurer","alliance_id":1165,"y":6113,"x":17086,"duel_level":156,"inLevelRange":1072,"inLevelRangeOpponent":-752,"isSleeping":false,"isSleepingFort":false,"isSleepingTent":false,"isFoundingFort":false,"alreadyDuelled":false,"last_duel":false,"nextDuel":null,"attackableByAnyone":false,"isDeadFlagged":false,"nextBattleAtLocation":null,"holiday_duel":true,"travel_distance":"0:08:33","exp":6462,"distance":513,"hp":1638,"rss":224,"rsp":353,"tct":95,"p":{"t":"t","id":92}},{"name":"Lee.the.Killer","player_id":184183,"level":175,"charclass":"soldier","alliance_id":1225,"y":17066,"x":30253,"duel_level":175,"inLevelRange":1205,"inLevelRangeOpponent":-847,"isSleeping":false,"isSleepingFort":false,"isSleepingTent":false,"isFoundingFort":false,"alreadyDuelled":false,"last_duel":false,"nextDuel":null,"attackableByAnyone":false,"isDeadFlagged":false,"nextBattleAtLocation":null,"holiday_duel":true,"travel_distance":"0:03:57","exp":7260,"distance":237,"hp":1867,"rss":210,"rsp":338,"tct":597,"p":{"t":"j","id":9}},{"name":"StephenMcTurner","player_id":591143,"level":199,"charclass":"worker","alliance_id":1165,"y":4657,"x":16613,"duel_level":208,"inLevelRange":1436,"inLevelRangeOpponent":-1012,"isSleeping":false,"isSleepingFort":false,"isSleepingTent":false,"isFoundingFort":false,"alreadyDuelled":false,"last_duel":false,"nextDuel":null,"attackableByAnyone":false,"isDeadFlagged":false,"nextBattleAtLocation":null,"holiday_duel":true,"travel_distance":"0:08:52","exp":8646,"distance":532,"hp":1884,"rss":1477,"rsp":1212,"tct":556,"p":{"t":"t","id":3077}},{"name":"Titus Santana","player_id":467067,"level":195,"charclass":"adventurer","alliance_id":1165,"y":4571,"x":15432,"duel_level":211,"inLevelRange":1457,"inLevelRangeOpponent":-1027,"isSleeping":false,"isSleepingFort":false,"isSleepingTent":false,"isFoundingFort":false,"alreadyDuelled":false,"last_duel":false,"nextDuel":null,"attackableByAnyone":false,"isDeadFlagged":false,"nextBattleAtLocation":null,"holiday_duel":true,"travel_distance":"0:09:11","exp":8772,"distance":551,"hp":1890,"rss":343,"rsp":496,"tct":741,"p":{"t":"j","id":95}},{"name":"Turbinikus","player_id":876794,"level":184,"charclass":"soldier","alliance_id":1525,"y":4130,"x":23450,"duel_level":184,"inLevelRange":1268,"inLevelRangeOpponent":-892,"isSleeping":false,"isSleepingFort":false,"isSleepingTent":false,"isFoundingFort":false,"alreadyDuelled":false,"last_duel":false,"nextDuel":null,"attackableByAnyone":false,"isDeadFlagged":false,"nextBattleAtLocation":null,"holiday_duel":true,"travel_distance":"0:07:12","exp":7638,"distance":432,"hp":1894,"rss":295,"rsp":313,"tct":296,"p":{"t":"t","id":363}},{"name":"Clagon","player_id":88462,"level":189,"charclass":"soldier","alliance_id":1225,"y":5670,"x":32211,"duel_level":189,"inLevelRange":1303,"inLevelRangeOpponent":-917,"isSleeping":false,"isSleepingFort":false,"isSleepingTent":false,"isFoundingFort":false,"alreadyDuelled":false,"last_duel":false,"nextDuel":null,"attackableByAnyone":false,"isDeadFlagged":false,"nextBattleAtLocation":null,"holiday_duel":true,"travel_distance":"0:04:56","exp":7848,"distance":296,"hp":1899,"rss":268,"rsp":276,"tct":341,"p":{"t":"j","id":106}},{"name":"John Wäyn","player_id":586829,"level":185,"charclass":"soldier","alliance_id":1225,"y":16468,"x":29124,"duel_level":185,"inLevelRange":1275,"inLevelRangeOpponent":-897,"isSleeping":false,"isSleepingFort":false,"isSleepingTent":false,"isFoundingFort":false,"alreadyDuelled":false,"last_duel":false,"nextDuel":null,"attackableByAnyone":false,"isDeadFlagged":false,"nextBattleAtLocation":null,"holiday_duel":true,"travel_distance":"0:04:17","exp":7680,"distance":257,"hp":1999,"rss":1586,"rsp":597,"tct":155,"p":{"t":"j","id":85}},{"name":"Haldan","player_id":1129356,"level":168,"charclass":"duelist","alliance_id":1225,"y":15879,"x":29741,"duel_level":168,"inLevelRange":1156,"inLevelRangeOpponent":-812,"isSleeping":false,"isSleepingFort":false,"isSleepingTent":false,"isFoundingFort":false,"alreadyDuelled":false,"last_duel":false,"nextDuel":null,"attackableByAnyone":false,"isDeadFlagged":false,"nextBattleAtLocation":null,"holiday_duel":true,"travel_distance":"0:04:08","exp":6966,"distance":248,"hp":2126,"rss":202,"rsp":417,"tct":95,"p":{"t":"t","id":73}},{"name":"Cymoril","player_id":141345,"level":195,"charclass":"worker","alliance_id":1165,"y":19299,"x":21629,"duel_level":195,"inLevelRange":1345,"inLevelRangeOpponent":-947,"isSleeping":false,"isSleepingFort":false,"isSleepingTent":false,"isFoundingFort":false,"alreadyDuelled":false,"last_duel":false,"nextDuel":null,"attackableByAnyone":false,"isDeadFlagged":false,"nextBattleAtLocation":null,"holiday_duel":true,"travel_distance":"0:06:29","exp":8100,"distance":389,"hp":2129,"rss":390,"rsp":354,"tct":293,"p":{"t":"j","id":44}},{"name":"Nili van Duke","player_id":457377,"level":172,"charclass":"soldier","alliance_id":1225,"y":13992,"x":24851,"duel_level":178,"inLevelRange":1226,"inLevelRangeOpponent":-862,"isSleeping":false,"isSleepingFort":false,"isSleepingTent":false,"isFoundingFort":false,"alreadyDuelled":false,"last_duel":false,"nextDuel":null,"attackableByAnyone":false,"isDeadFlagged":false,"nextBattleAtLocation":null,"holiday_duel":true,"travel_distance":"0:05:39","exp":7386,"distance":339,"hp":2248,"rss":259,"rsp":320,"tct":557,"p":{"t":"j","id":32}},{"name":"talu","player_id":1145985,"level":187,"charclass":"adventurer","alliance_id":1225,"y":4145,"x":2121,"duel_level":187,"inLevelRange":1289,"inLevelRangeOpponent":-907,"isSleeping":false,"isSleepingFort":false,"isSleepingTent":false,"isFoundingFort":false,"alreadyDuelled":false,"last_duel":false,"nextDuel":null,"attackableByAnyone":false,"isDeadFlagged":false,"nextBattleAtLocation":null,"holiday_duel":true,"travel_distance":"0:12:52","exp":7764,"distance":772,"hp":2275,"rss":895,"rsp":1164,"tct":20,"p":{"t":"t","id":326}},{"name":"AnnyOmcd","player_id":660212,"level":173,"charclass":"soldier","alliance_id":1165,"y":2711,"x":2076,"duel_level":173,"inLevelRange":1191,"inLevelRangeOpponent":-837,"isSleeping":false,"isSleepingFort":false,"isSleepingTent":false,"isFoundingFort":false,"alreadyDuelled":false,"last_duel":false,"nextDuel":null,"attackableByAnyone":false,"isDeadFlagged":false,"nextBattleAtLocation":null,"holiday_duel":true,"travel_distance":"0:13:01","exp":7176,"distance":781,"hp":2591,"rss":679,"rsp":799,"tct":162,"p":{"t":"j","id":68}},{"name":"Thurstan de Crusoe","player_id":559636,"level":198,"charclass":"soldier","alliance_id":1165,"y":10802,"x":14735,"duel_level":228,"inLevelRange":1576,"inLevelRangeOpponent":-1112,"isSleeping":false,"isSleepingFort":false,"isSleepingTent":false,"isFoundingFort":false,"alreadyDuelled":false,"last_duel":false,"nextDuel":null,"attackableByAnyone":false,"isDeadFlagged":false,"nextBattleAtLocation":null,"holiday_duel":true,"travel_distance":"0:08:45","exp":9486,"distance":525,"hp":3082,"rss":518,"rsp":596,"tct":279,"p":{"t":"j","id":55}},{"name":"dsa8088","player_id":256247,"level":208,"charclass":"soldier","alliance_id":1225,"y":15879,"x":29741,"duel_level":208,"inLevelRange":1436,"inLevelRangeOpponent":-1012,"isSleeping":false,"isSleepingFort":false,"isSleepingTent":false,"isFoundingFort":false,"alreadyDuelled":false,"last_duel":false,"nextDuel":null,"attackableByAnyone":false,"isDeadFlagged":false,"nextBattleAtLocation":null,"holiday_duel":true,"travel_distance":"0:04:08","exp":8646,"distance":248,"hp":3228,"rss":185,"rsp":573,"tct":216,"p":{"t":"t","id":73}},{"name":"quis","player_id":746,"level":192,"charclass":"soldier","alliance_id":1165,"y":4340,"x":5325,"duel_level":192,"inLevelRange":1324,"inLevelRangeOpponent":-932,"isSleeping":false,"isSleepingFort":false,"isSleepingTent":false,"isFoundingFort":false,"alreadyDuelled":false,"last_duel":false,"nextDuel":null,"attackableByAnyone":false,"isDeadFlagged":false,"nextBattleAtLocation":null,"holiday_duel":true,"travel_distance":"0:11:58","exp":7974,"distance":718,"hp":3342,"rss":236,"rsp":436,"tct":198,"p":{"t":"j","id":58}},{"name":"tesaiga0815","player_id":875297,"level":191,"charclass":"soldier","alliance_id":1225,"y":17092,"x":28580,"duel_level":201,"inLevelRange":1387,"inLevelRangeOpponent":-977,"isSleeping":false,"isSleepingFort":false,"isSleepingTent":false,"isFoundingFort":false,"alreadyDuelled":false,"last_duel":false,"nextDuel":null,"attackableByAnyone":false,"isDeadFlagged":false,"nextBattleAtLocation":null,"holiday_duel":true,"travel_distance":"0:04:26","exp":8352,"distance":266,"hp":3757,"rss":273,"rsp":274,"tct":333,"p":{"t":"j","id":93}},{"name":"Chamberlin","player_id":580770,"level":188,"charclass":"soldier","alliance_id":1165,"y":12623,"x":12261,"duel_level":188,"inLevelRange":1296,"inLevelRangeOpponent":-912,"isSleeping":false,"isSleepingFort":false,"isSleepingTent":false,"isFoundingFort":false,"alreadyDuelled":false,"last_duel":false,"nextDuel":null,"attackableByAnyone":false,"isDeadFlagged":false,"nextBattleAtLocation":null,"holiday_duel":true,"travel_distance":"0:09:22","exp":7806,"distance":562,"hp":3824,"rss":284,"rsp":368,"tct":171,"p":{"t":"j","id":19}},{"name":"Auriga","player_id":655162,"level":187,"charclass":"soldier","alliance_id":1165,"y":7174,"x":3784,"duel_level":189,"inLevelRange":1303,"inLevelRangeOpponent":-917,"isSleeping":false,"isSleepingFort":false,"isSleepingTent":false,"isFoundingFort":false,"alreadyDuelled":false,"last_duel":false,"nextDuel":null,"attackableByAnyone":false,"isDeadFlagged":false,"nextBattleAtLocation":null,"holiday_duel":true,"travel_distance":"0:12:09","exp":7848,"distance":729,"hp":3847,"rss":738,"rsp":1002,"tct":74,"p":{"t":"j","id":87}}]